odoo/addons/pos_sale_order_load/__init__.py
odoo/addons/pos_sale_order_load/__manifest__.py
odoo/addons/pos_sale_order_load/i18n/fr.po
odoo/addons/pos_sale_order_load/i18n/pos_sale_order_load.pot
odoo/addons/pos_sale_order_load/models/__init__.py
odoo/addons/pos_sale_order_load/models/sale_order.py
odoo/addons/pos_sale_order_load/static/src/js/SaleOrderLoadButton.js
odoo/addons/pos_sale_order_load/static/src/js/models.js
odoo/addons/pos_sale_order_load/static/src/js/pos_sale_order_load.js
odoo/addons/pos_sale_order_load/static/src/xml/SaleOrderLoadButton.xml
odoo/addons/pos_sale_order_load/templates/assets.xml
odoo/addons/pos_sale_order_load/tests/__init__.py
odoo/addons/pos_sale_order_load/tests/test_load_order.py
odoo/addons/pos_sale_order_load/views/sale_order.xml
odoo14_addon_pos_sale_order_load-14.0.1.1.0.dist-info/METADATA
odoo14_addon_pos_sale_order_load-14.0.1.1.0.dist-info/WHEEL
odoo14_addon_pos_sale_order_load-14.0.1.1.0.dist-info/top_level.txt
odoo14_addon_pos_sale_order_load-14.0.1.1.0.dist-info/RECORD
